Metadata-Version: 2.1
Name: trello-api-wrapper
Version: 0.0.12
Summary: Object oriented Python wrapper for Trello API
Home-page: https://github.com/JordyAraujo/Trello_Api_Wrapper
Author: Jordy Araújo
Author-email: jordyaraujo@outlook.com
License: MIT License
Keywords: trello api wrapper
Platform: UNKNOWN
License-File: LICENSE
